{
  "smith": {
    "0": {
      "A": "你好\n我是這村子唯一的鐵匠…\n這邊有許多武器\n想要買什麼?",
      "B": [
        "交易/trade",
        "任務/goto [quest=q01]",
        "離開/exit"
      ]
    },
    "q01": {
      "A": "殺死半獸人",
      "B": [
        "接受/quest q01",
        "離開/exit"
      ]
    },
    "q01_open": {
      "A": "...",
      "B": [
        "離開/exit"
      ]
    },
    "q01_finish": {
      "A": "...",
      "B": [
        "任務完成了/goto none;close q01;set quest none"
      ]
    },
    "none": {
      "A": "...",
      "B": [
        "離開/exit"
      ]
    }
  }
}